merge_lookup_script/__init__.py
merge_lookup_script/lld_collect_xls.py
merge_lookup_script/merge_vl.py
merge_lookup_script/plot_ttd_moat.py
merge_lookup_script/ttd_lld.py
merge_lookup_script/tests/__init__.py
merge_lookup_script/tests/bulk_screenshot.py
merge_lookup_script/tests/test_lld_collect_xls.py
merge_lookup_script/tests/test_merge_vl.py
merge_lookup_script/tests/test_ttd_lld.py
merge_lookup_pkg_chickachickaaa-1.0.0.dist-info/LICENSE.txt
merge_lookup_pkg_chickachickaaa-1.0.0.dist-info/METADATA
merge_lookup_pkg_chickachickaaa-1.0.0.dist-info/WHEEL
merge_lookup_pkg_chickachickaaa-1.0.0.dist-info/top_level.txt
merge_lookup_pkg_chickachickaaa-1.0.0.dist-info/RECORD
