Metadata-Version: 2.1
Name: merge-lookup-pkg-chickachickaaa
Version: 1.0.0
Summary: A script to merge large files into one excel and then do a vlookup.
Home-page: https://github.com/chickachickaaa/merge_lookup
Author: T. Higgins
Author-email: thiggins4890@gmail.com
License: UNKNOWN
Platform: UNKNOWN
Classifier: Programming Language :: Python :: 3
Classifier: License :: OSI Approved :: MIT License
Classifier: Operating System :: OS Independent
